{
    "의안접수정보": {
        "의안번호": [
            "2007243"
        ],
        "제안일자": [
            "2017-06-07"
        ],
        "제안자": [
            "나경원의원등10인"
        ],
        "문서": [
            "의안원문"
        ],
        "제안회기": [
            "제20대(2016~2020)제351회"
        ],
        "제안이유 및 주요내용": "제안이유 및 주요내용\n\n  지방자치단체의 정책 입안 및 집행 과정에서 여러 가지 복잡한 법적 문제들이 얽혀 있음에도 불구하고 이를 충분히 검토하지 않고 정책을 집행할 경우 해당 지방자치단체에 상당한 피해가 우려되고, 또한 그로 인한 피해는 모두 주민들에게 돌아가게 됨.\n  한편, 지방자치단체 주민들의 권리의식이 강화됨에 따라 지자체의 잘못된 정책 집행과 관련한 소송이 급격히 증가하고 있으며 이로 인하여 상당한 사회적·경제적 손실이 발생하고 있다고 하겠음.\n  그러나 지방자치단체 중 직제에 법무담당관을 둔 곳은 극히 일부에 불과하고, 법무담당관을 두고 있는 곳에서도 법률전문가인 변호사가 없는 경우가 많아서 지자체가 법적 문제에 효율적으로 대처하지 못하는 측면이 있음.\n  이에 지방자치단체에 변호사의 자격을 가진 법무담당관을 두도록 의무화함으로써 지자체의 행정 효율성과 적법성을 제고하는데 기여하려는 것임(안 제112조의2 신설)."
    },
    " 소관위 심사정보": {
        "소관위원회": [
            "행정안전위원회"
        ],
        "회부일": [
            "2017-06-08"
        ],
        "상정일": [
            "2017-11-23"
        ],
        "처리일": [
            ""
        ],
        "처리결과": [
            ""
        ],
        "문서": [
            "검토보고서"
        ]
    },
    "소관위 회의정보": {
        "회의명": [
            "제354회국회(정기회)제5차전체회의"
        ],
        "회의일": [
            "2017-11-23"
        ],
        "회의결과": [
            "상정/검토보고/대체토론/소위회부"
        ],
        "회의록": [
            ""
        ]
    },
    "본회의 심의정보": {
        "상정일": [
            ""
        ],
        "의결일": [
            "2020-05-29"
        ],
        "회의명": [
            ""
        ],
        "회의결과": [
            "임기만료폐기"
        ],
        "회의록": [
            ""
        ]
    }
}