{
    "의안접수정보": {
        "의안번호": [
            "2019948"
        ],
        "제안일자": [
            "2019-04-22"
        ],
        "제안자": [
            "김두관의원등12인"
        ],
        "문서": [
            "의안원문비용추계서"
        ],
        "제안회기": [
            "제20대(2016~2020)제368회"
        ],
        "제안이유 및 주요내용": "제안이유 및 주요내용\n\n  지역간의 불균형을 해소하고, 지역의 특성에 맞는 자립적 발전을 위해 현행법이 제정되어 국가 및 지방자치단체는 지역간의 균형있는 발전과 지역의 특성에 맞는 자립적 발전을 위하여 지역주도의 관련 시책을 수립하고 추진하고 있음.\n  그리고 정부는 국가균형발전 5개년 계획을 수립하여 지역의 혁신체계를 구축하고, 지역산업 육성 및 일자리 창출, 교육여건 개선과 인재양성, 지역문화와 관광의 육성, 지역의 복지 및 보건의료의 확충과 관련된 시책을 국가 및 지방자치단체가 추진하도록 되어있음. \n  그러나 최근 국민들의 생활체육 활성화와 시설 확충과 관련된 사업들에 대한 요구가 높아지고 있고, 정부에서도 생활 SOC의 일환으로 생활체육시설 확충을 추진하고 있는 상황임.\n  이에 국가와 지방자치단체가 생활체육시설 격차 해소와 시설 기반 조성 및 정비, 학교의 체육시설 개선 및 주민의 건강 및 생활체육시설을 위한 시책을 마련하여 추진하고자 함(안 제15조의3 신설)."
    },
    " 소관위 심사정보": {
        "소관위원회": [
            "산업통상자원중소벤처기업위원회"
        ],
        "회부일": [
            "2019-04-23"
        ],
        "상정일": [
            "2019-07-12"
        ],
        "처리일": [
            ""
        ],
        "처리결과": [
            ""
        ],
        "문서": [
            "검토보고서"
        ]
    },
    "소관위 회의정보": {
        "회의명": [
            "제369회국회(임시회)제3차전체회의"
        ],
        "회의일": [
            "2019-07-12"
        ],
        "회의결과": [
            "상정/제안설명/검토보고/대체토론/소위회부"
        ],
        "회의록": [
            ""
        ]
    },
    "관련위 심사정보": {
        "관련위원회": [
            "행정안전위원회"
        ],
        "회부일": [
            "2019-04-23"
        ],
        "상정일": [
            ""
        ],
        "의견서제시일": [
            ""
        ],
        "문서": [
            ""
        ]
    },
    "본회의 심의정보": {
        "상정일": [
            ""
        ],
        "의결일": [
            "2020-05-29"
        ],
        "회의명": [
            ""
        ],
        "회의결과": [
            "임기만료폐기"
        ],
        "회의록": [
            ""
        ]
    }
}