{
    "의안접수정보": {
        "의안번호": [
            "1805159"
        ],
        "제안일자": [
            "2009-06-17"
        ],
        "제안자": [
            "최철국의원등17인"
        ],
        "문서": [
            "의안원문"
        ],
        "제안회기": [
            "제18대(2008~2012)제282회"
        ],
        "제안이유 및 주요내용": "제안이유\n  현행법에서는 총사업비가 500억원 이상이고 국가의 재정지원 규모가 300억원 이상인 대규모사업에 대한 예산을 편성하기 위해서는 미리 예비타당성조사를 실시하여야 한다고 규정하고 있음에도 국회에 제출할 때 첨부해야 할 서류에 예비타당성조사 결과보고서가 포함돼 있지 않아 예산 심사를 효율적으로 수행하지 못하고 있음. \n 또한, 정부는 「국가재정법」제정 및 그에 따른 재정제도의 변화를 뒷받침하고 재정운용의 효율성과 투명성을 제고하기 위해 「디지털예산회계시스템」을 구축하고 예산의 요구, 편성, 집행, 결산 등 재정운용의 전 과정을 통합적으로 관리하고 있음. \n  그러나 현행법에서는 기획재정부장관의 “재정에 관한 업무를 원활하게 수행하기 위하여 정보통신매체 및 프로그램 등을 개발” 할 수 있도록 하고 국가회계업무와 관련된 정보시스템 개발 시 감사원과의 협의를 규정하고 있을 뿐, 국가재정정보에 대한 국회의 접근과 활용에 대해서는 아무런 규정이 없음. \n 따라서 국회 예산심의권 기능을 강화하기 위하여 예산을 국회에 제출할 때 첨부해야 할 서류에 예비타당성조사 결과보고서를 포함하도록 하고, 「국회법」이 규정하고 있는 자료 및 서류제출요구권의 성격, 국회의 예산안 심사 및 결산 심의 업무의 중요성과 방대함 등을 고려해 「국가재정법」국가재정정보에 대한 국회의 접근과 활용에 대한 규정을 명문화하고 이에 대한 기획재정부장관의 책임을 명문화 하려는 것임. \n\n주요내용\n가. 예산안을 국회 제출할 때 예비타당성조사 결과보고서를 함께 제출하도록 함. (안 제34조제14호 신설) \n나. 정보통신 매체 및 프로그램 등을 통하여 생성되는 정보에 국회가 접근하여 예산안 및 결산심의 등의 업무 수행에 활용할 수 있도록 함.(안 제97조의2제3항)"
    },
    " 소관위 심사정보": {
        "소관위원회": [
            "기획재정위원회"
        ],
        "회부일": [
            "2009-06-18"
        ],
        "상정일": [
            "2009-09-14"
        ],
        "처리일": [
            ""
        ],
        "처리결과": [
            ""
        ],
        "문서": [
            "검토보고서"
        ]
    },
    "소관위 회의정보": {
        "회의명": [
            "제284회국회(정기회)제2차전체회의",
            "제284회국회(정기회)제1차경제재정소위",
            "제294회국회(정기회)제1차경제재정소위",
            "제297회국회(임시회)제1차경제재정소위",
            "제297회국회(임시회)제2차경제재정소위",
            "제297회국회(임시회)제3차경제재정소위",
            "제297회국회(임시회)제4차경제재정소위",
            "제297회국회(임시회)제5차경제재정소위",
            "제298회국회(임시회)제1차경제재정소위",
            "제298회국회(임시회)제2차경제재정소위",
            "제299회국회(임시회)제1차경제재정소위",
            "제299회국회(임시회)제2차경제재정소위",
            "제299회국회(임시회)제3차경제재정소위",
            "제299회국회(임시회)제4차경제재정소위",
            "제301회국회(임시회)제1차경제재정소위",
            "제301회국회(임시회)제2차경제재정소위",
            "제302회국회(임시회)제1차경제재정소위",
            "제302회국회(임시회)제2차경제재정소위",
            "제302회국회(임시회)제3차경제재정소위",
            "제303회국회(정기회)제1차경제재정소위",
            "제303회국회(정기회)제2차경제재정소위",
            "제304회국회(임시회)제1차경제재정소위",
            "제304회국회(임시회)제2차경제재정소위"
        ],
        "회의일": [
            "2009-09-14",
            "2009-09-15",
            "2010-11-16",
            "2011-02-22",
            "2011-02-23",
            "2011-02-24",
            "2011-02-25",
            "2011-03-02",
            "2011-03-03",
            "2011-03-07",
            "2011-04-06",
            "2011-04-07",
            "2011-04-11",
            "2011-04-12",
            "2011-06-08",
            "2011-06-22",
            "2011-08-18",
            "2011-08-22",
            "2011-08-25",
            "2011-11-07",
            "2011-11-14",
            "2011-12-22",
            "2011-12-23"
        ],
        "회의결과": [
            "상정/제안설명/검토보고/대체토론/소위회부",
            "상정",
            "상정",
            "상정",
            "상정",
            "상정",
            "상정",
            "상정",
            "상정",
            "상정",
            "상정",
            "상정",
            "상정",
            "상정",
            "상정",
            "상정",
            "상정",
            "상정",
            "상정",
            "상정",
            "상정",
            "상정",
            "상정"
        ],
        "회의록": [
            "",
            "",
            "",
            "",
            "",
            "",
            "",
            "",
            "",
            "",
            "",
            "",
            "",
            "",
            "",
            "",
            "",
            "",
            "",
            "",
            "",
            "",
            ""
        ]
    },
    "본회의 심의정보": {
        "상정일": [
            ""
        ],
        "의결일": [
            "2012-05-29"
        ],
        "회의명": [
            ""
        ],
        "회의결과": [
            "임기만료폐기"
        ],
        "회의록": [
            ""
        ]
    }
}