{
    "의안접수정보": {
        "의안번호": [
            "162348"
        ],
        "제안일자": [
            "2003-06-04"
        ],
        "제안자": [
            "김효석의원등33인"
        ],
        "문서": [
            "의안원문"
        ],
        "제안회기": [
            "제16대(2000~2004)제240회"
        ],
        "제안이유 및 주요내용": "■ 제안이유\n세계무역기구(WTO)체제 출범 이후 농축수산물의 시장개방과 특히 도하개발아젠다(DDA) 농업협상 및 자유무역협정(FTA)의 진전에 따라 국제 경쟁력이 취약한 농수산업부문에서는 농어가 소득의 감소 및 부채의 증가로 어려움이 더욱 가중될 것으로 예상되는 바, 농어가의 생산비 부담경감 및 생산자단체·서민 금융기관의 농어가 등 영세서민의 실익사업 수행을 위한 각종 조세지원시한이 2003년말로 만료될 예정에 있어 국제경쟁력의 확보, 농어업인의 영농?영어 의욕의 고취 및 농어업 생산자단체?서민 금융기관의 자생력 확보를 위하여 세제상의 지원시한을 연장하려는 것임.\n\n■ 주요골자\n1. 농업·농촌기본법에 의한 영농조합법인의 농업소득 등에 대한 법인세, 조합원의 배당소득에 대한 소득세, 농업인이 농지 또는 초지를 영농조합법인에 현물출자함으로써 발생하는 소득에 대한 양도소득세 등의 면제시한을 2006년 12월 31일로 3년 연장함(안 제66조).\n2. 수산업법에 의한 영어조합법인의 각 사업연도 소득에 대한 법인세, 조합원의 배당소득에 대한 소득세, 어업인이 어업용 토지 등을 영어조합법인에 현물출자함으로써 발생하는 소득에 대한 양도소득세 등의 면제시한을 2006년 12월 31일로 3년 연장함(안 제67조).\n3. 농업?농촌기본법에 의한 농업회사법인의 농업소득 등에 대한 법인세, 농업인이 농지 또는 초지를 농업회사법인에 현물출자함으로써 발생하는 소득에 대한 양도소득세 등의 면제시한을 2006년 12월 31일로 3년 연장함(안 제68조).\n4. 농업협동조합·수산업협동조합·산림조합 등 조합법인에 대하여 당기순이익에 12%의 세율을 적용하여 과세하는 법인세 과세특례 적용시한을 3년 연장함(안 제72조제1항).\n5. 농업협동조합중앙회?수산업협동조합중앙회?산림조합중앙회의 수익사업 소득금액 중 대통령령이 정하는 금액을 고유목적사업준비금으로 손금 산입할 수 있도록 하는 시한을 2006년 12월 31일 이내에 종료하는 사업연도까지 적용토록 하여 3년 연장함(안 제74조제2항).\n6. 농어가 목돈 마련 저축의 이자 소득에 대한 소득세 비과세 시한을 3년 연장함.(안 제88조의 7).\n7. 농민·어민 등을 조합원으로 하는 금융기관 등의 1인당 2천만원 이하 예탁금의 이자소득에 대한 비과세시한을 2006년 12월 31일까지 3년 연장함(안 제89조의3). \n8. 비료?농약?농기계 등 농림업용 기자재와 연근해 및 내수면어업용으로 사용하는 어업용기자재에 대한 부가가치세 영세율 적용시한을 2006년 12월 31일까지 3년 연장함(안 제105조제1항)."
    },
    " 소관위 심사정보": {
        "소관위원회": [
            "재정경제위원회"
        ],
        "회부일": [
            "2003-06-05"
        ],
        "상정일": [
            "2003-06-13"
        ],
        "처리일": [
            "2003-11-21"
        ],
        "처리결과": [
            "대안반영폐기"
        ],
        "문서": [
            "검토보고서심사보고서"
        ]
    },
    "소관위 회의정보": {
        "회의명": [
            "제240회국회(임시회)제1차전체회의"
        ],
        "회의일": [
            "2003-06-13"
        ],
        "회의결과": [
            "상정/상정"
        ],
        "회의록": [
            ""
        ]
    },
    "본회의 심의정보": {
        "상정일": [
            ""
        ],
        "의결일": [
            "2003-12-09"
        ],
        "회의명": [
            ""
        ],
        "회의결과": [
            "대안반영폐기"
        ],
        "회의록": [
            ""
        ]
    }
}