{
    "의안접수정보": {
        "의안번호": [
            "1900361"
        ],
        "제안일자": [
            "2012-06-28"
        ],
        "제안자": [
            "김기선의원등21인"
        ],
        "문서": [
            "의안원문"
        ],
        "제안회기": [
            "제19대(2012~2016)제308회"
        ],
        "제안이유 및 주요내용": "제안이유 및 주요내용\n\n  보건복지부가 발표한 ‘2011년도 전국아동학대현황보고서’에 따르면 어린이집, 복지시설, 학교, 병원 등 가정 외의 장소에서의 아동학대가 전체 아동학대 건수의 약 13%를 차지하고 있는 것으로 파악되고 있음.\n  그러나 현행법은 아동학대범죄로 처벌을 받은 아동학대 경력자가 아동관련기관 등에 취업하는 것에 대한 규제가 없어 아동관련기관을 이용하는 아동이 아동학대에 노출될 위험이 매우 높아 이에 대한 대책이 요구되고 있음.\n  따라서 아동학대 경력자가 아동관련기관에 취업하는 것을 제한하는 규정을 신설하여 우리 헌법이 국가에게 부과하고 있는 국민의 기본권보호의무의 이행을 보다 충실히 하려는 것임(안 제29조의2 및 제29조의3 신설 등)."
    },
    " 소관위 심사정보": {
        "소관위원회": [
            "보건복지위원회"
        ],
        "회부일": [
            "2012-07-09"
        ],
        "상정일": [
            "2012-08-24"
        ],
        "처리일": [
            "2013-06-20"
        ],
        "처리결과": [
            "대안반영폐기"
        ],
        "문서": [
            "검토보고서심사보고서"
        ]
    },
    "소관위 회의정보": {
        "회의명": [
            "제310회국회(임시회)제1차전체회의",
            "제315회국회(임시회)제1차전체회의",
            "제316회국회(임시회)제1차법안심사소위",
            "제316회국회(임시회)제3차법안심사소위"
        ],
        "회의일": [
            "2012-08-24",
            "2013-04-12",
            "2013-06-18",
            "2013-06-20"
        ],
        "회의결과": [
            "상정",
            "상정/제안설명/검토보고/대체토론/소위회부",
            "상정/축조심사",
            "상정/축조심사/의결(대안반영폐기)"
        ],
        "회의록": [
            "",
            "",
            "",
            ""
        ]
    },
    "본회의 심의정보": {
        "상정일": [
            ""
        ],
        "의결일": [
            "2013-12-31"
        ],
        "회의명": [
            ""
        ],
        "회의결과": [
            "대안반영폐기"
        ],
        "회의록": [
            ""
        ]
    }
}