{
    "의안접수정보": {
        "의안번호": [
            "171618"
        ],
        "제안일자": [
            "2005-04-11"
        ],
        "제안자": [
            "강혜숙의원등26인"
        ],
        "문서": [
            "의안원문"
        ],
        "제안회기": [
            "제17대(2004~2008)제253회"
        ],
        "제안이유 및 주요내용": "■ 제안이유 및 주요내용\n\n  현재 성인오락실을 운영하는 게임제공업자가 문화관광부장관 고시로 정하여 경품으로 제공할 수 있는 상품권 등을 경품으로 제공하고 이를 받은 게임물이용자가 이를 다시 현금으로 환산함으로써 사행행위가 과다하게 조장되거나 도박중독자가 양산되는 등의 사회에 부정적인 영향을 미치고 있음.\n  이에 문화관광부장관이 경품으로 제공할 수 있는 경품의 종류를 한정하여 이러한 부작용을 근절할 수 있는 법적 근거를 마련하려는 것임(안 제32조제3호)."
    },
    " 소관위 심사정보": {
        "소관위원회": [
            "문화관광위원회"
        ],
        "회부일": [
            "2005-04-13"
        ],
        "상정일": [
            "2005-11-17"
        ],
        "처리일": [
            "2005-12-06"
        ],
        "처리결과": [
            "대안반영폐기"
        ],
        "문서": [
            "검토보고서심사보고서"
        ]
    },
    "소관위 회의정보": {
        "회의명": [
            "제256회국회(정기회)제13차전체회의"
        ],
        "회의일": [
            "2005-11-17"
        ],
        "회의결과": [
            "상정/상정"
        ],
        "회의록": [
            ""
        ]
    },
    "본회의 심의정보": {
        "상정일": [
            ""
        ],
        "의결일": [
            "2006-04-06"
        ],
        "회의명": [
            ""
        ],
        "회의결과": [
            "대안반영폐기"
        ],
        "회의록": [
            ""
        ]
    }
}