{
    "의안접수정보": {
        "의안번호": [
            "173588"
        ],
        "제안일자": [
            "2005-12-08"
        ],
        "제안자": [
            "산업자원위원장"
        ],
        "문서": [
            "의안원문"
        ],
        "제안회기": [
            "제17대(2004~2008)제256회"
        ],
        "제안이유 및 주요내용": "■ 제안경위\n가. 2004년 12월 15일 정부가 제출한 「에너지기본법안」 및 2005년 1월 11일 김성조의원 등 25인이 발의한 「에너지기본법안」은 제252회 국회(임시회) 제1차 위원회(2005. 2. 18)에서 공청회를 실시하였으며, 제2차 위원회(2005. 2. 21)에서 대체토론을 거쳐 각각 법안심사소위원회에 회부하였음.\n 나. 2005년 4월 11일 조승수의원 등 10인이 발의한 「에너지기본법안」은 제254회 국회(임시회) 제4차 위원회(2005. 6. 20)에서 대체토론을 거쳐 법안심사소위원회에 회부하였음.\n 다. 법안심사소위원회에서는 2005년 2월 22일과 23일, 4월 21일 세 차례에 걸쳐 정부가 제출한 「에너지기본법안」과 김성조의원이 대표발의한 「에너지기본법안」에 대하여 심사를 하였으며, 2005년 6월 21일과 11월 18일 두 차례에 걸쳐 정부가 제출한 「에너지기본법안」, 김성조의원이 대표발의한 「에너지기본법안」 및 조승수의원이 대표발의한 「에너지기본법안」 이상 3건의 법률안을 병합하여 심사한 결과, 이들 법률안을 통합하여 위원회대안을 마련하고 2건의 의원발의안과 정부제출안은 각각 본회의에 부의하지 아니하기로 하였으며, 이를 제256회 국회(정기회) 제10차 위원회(2005. 11. 22)에 보고하여 의결함으로써 위원회대안을 제안하게 된 것임.\n\n■ 제안이유\n\n  현행 에너지 관련 법체계는 별도의 기본법이나 일반법 없이 에너지원별 및 기능별 개별법이 수평적인 법체계를 구성하고 있어서 에너지관련 정책 및 계획을 통합적으로 수립·관리하기에는 역부족인 실정임. 따라서 에너지기본법을 제정하여 에너지정책에 대한 장기적·통합적 비전을 제시하고, 에너지정책의 기본원칙을 천명하며, 에너지 관련 개별법 및 정책의 유기적 연계성을 강화함으로써 에너지빈국인 우리나라가 급변하는 국제에너지시장의 여건변화에 능동적으로 대처할 수 있는 기반을 조성하고, 나아가 에너지정책의 환경친화성, 사회적 수용성 및 형평성도 제고함으로써 국민경제의 지속가능한 발전과 국민의 복리향상에 기여하려는 것임.\n\n\n\n■ 주요내용\n\n가. 에너지정책 및 관련계획은 에너지의 안정적 공급 실현, 환경친화적 에너지의 생산 및 사용 확대, 에너지 저소비형 경제사회구조로의 전환을 위한 에너지수요관리의 지속적 강화, 에너지 관련 모든 분야에 대한 통합적 고려, 에너지산업에 대한 시장경쟁 요소의 도입 확대 및 규제완화 등의 시책 추진, 에너지 사용의 형평성을 제고하기 위한 노력의 지속적 추진 등의 원칙에 따라 수립·시행되어야 함(안 제3조).\n나. 정부는 5년마다 20년을 계획기간으로 국가에너지기본계획을 국가에너지위원회의 심의를 거쳐 수립하고, 특별시장ㆍ광역시장 또는 도지사는 5년마다 5년 이상을 계획기간으로 하는 지역에너지기본계획을 수립해야 함(안 제6조 및 제7조).\n다. 주요 에너지정책 및 에너지관련계획에 관한 사항을 심의ㆍ조정하기 위하여 대통령을 위원장으로 하는 국가에너지위원회를 설치ㆍ운영함(안 제9조 내지 제10조). \n라. 정부는 에너지 관련 기술의 개발과 보급을 촉진하기 위하여 5년마다 10년 이상을 계획기간으로 하는 에너지기술개발계획을 수립하고, 이에 따른 연차별 실행계획을 수립·시행하여야 함(안 제11조).\n마. 국가 및 지방자치단체는 이 법의 목적을 달성하기 위하여 필요한 행정 및 재정상의 조치를 마련하고 재정지원을 함(안 제16조).\n바. 산업자원부장관이 에너지관련 통계 등 실태조사 및 에너지총조사를 실시할 수 있도록 함(안 제18조).\n사. 정부는 매년 주요 에너지정책의 집행경과 및 결과를 국회에 보고하도록 함(안 제19조)."
    },
    " 소관위 심사정보": {
        "소관위원회": [
            "산업자원위원회"
        ],
        "회부일": [
            ""
        ],
        "상정일": [
            ""
        ],
        "처리일": [
            ""
        ],
        "처리결과": [
            "대안가결"
        ],
        "문서": [
            ""
        ]
    },
    "법사위 체계자구심사정보": {
        "공포일자": [
            "2006-03-03"
        ],
        "공포번호": [
            "7860"
        ],
        "공포법률": [
            "에너지기본법"
        ]
    },
    "법사위 회의정보": {
        "회의명": [
            "제17회국회(임시회)제256차전체회의"
        ],
        "회의일": [
            "2005-12-07"
        ],
        "회의결과": [
            "상정/상정"
        ],
        "회의록": [
            ""
        ]
    },
    "본회의 심의정보": {
        "상정일": [
            "2006-02-09"
        ],
        "의결일": [
            "2006-02-09"
        ],
        "회의명": [
            "제258회국회(임시회)제3차본회의"
        ],
        "회의결과": [
            "원안가결"
        ],
        "회의록": [
            ""
        ]
    },
    "정부이송정보": {
        "정부이송일": [
            "2006-02-17"
        ]
    }
}