{
    "의안접수정보": {
        "의안번호": [
            "150844"
        ],
        "제안일자": [
            "1997-11-12"
        ],
        "제안자": [
            "정동채의원등9인외69인"
        ],
        "문서": [
            "의안원문의안원문"
        ],
        "제안회기": [
            "제15대(1996~2000)제185회"
        ],
        "제안이유 및 주요내용": "■ 제안이유\n\n교육방송은 현재 운영예산의 일부가 정부출연금, 공익자금에서 지원되고 있으나 안정적인 재원이 확보되지 않\n아 파행적으로 운영되고 있다. 또한 방송편성 내용이 평생교육과 사회교육보다는 학교교육의 과외방송에 치중\n되고 있는 한계를 노정하고 있다. \n따라서 방송의 교육적 기능을 제고함과 동시에 각계층(여성, 노인, 청소년, 장애인 등)의 교양프로그램까지 포\n괄할 수 있는 교육방송의 주체로서 ‘한국교육방송공사’를 설립할 수 있게 하기 위하여 ‘한국교육방송공사법\n’을 제정하려는 것이다.\n\n\n\n■ 주요골자\n\n1.  이 법은 한국교육방송공사(이하 “공사”라 한다)를 설립하여 교육방송을 효율적으로 실시함으로써 지속적\n    인 사회교육 평생교육 학교교육을 보완하고 민주적 교육발전에 이바지함을 목적으로 함(안 제1조)\n\n2.  공사의 자본금은 정부가 전액 출자하도록 함(안 제4조)\n\n3.  공사가 정관을 제정하거나 변경한 경우에 방송위원회의 승인을 얻도록 함(안 제5조)\n\n4.  공사 경영에 관한 최고의결기관으로 이사회를 두고, 이사장을 포함한 9인의 이사를 교육 문화 과학 방송 \n    등 각분야의 전문성과 각계의 대표성을 고려하여 방송위원회에서 선출하도록 함(안 제9조)\n\n5.  이사의 임기를 4년으로 함(안 제10조)\n\n6.  공사의 공공성을 보장할 수 있게 하기 위하여 이사의 결격사유를 규정한 조항을 둠(안 제12조)\n\n7.  이사회의 심의 의결 사항으로 공사가 행하는 방송의 종합적인 기본 계획, 공사의 경영평가 및 공표, 사장 \n    감사의 선출과 부사장 및 본부장의 임명동의 등을 둠(안 제13조)\n\n8.  이사의 직무상 독립과 신분보장에 관한 조항을 둠(안 제14조)\n\n9.  이사가 심의 의결에 간여할 수 없는 제척사항을 규정한 조항을 둠(안 제15조)\n\n10. 이사회의 회의내용 공개를 의무화하도록 함(안 제16조)\n\n11. 이사회는 재적이사의 과반수 찬성으로 의결하도록 함(안 제17조)\n\n12. 공사에 집행기관으로 사장 1인, 부사장 1인, 5인 이내의 본부장, 감사 1인을 두고, 공사의 사장은 이사회\n    에서 직접 선출하도록 함(안 제18조)\n\n13. 사장, 부사장, 본부장, 감사의 임기를 각각 3년으로 함(안 제19조)\n\n14. 공사의 전문성을 제고하기 위해 이사회가 필요하다고 인정할 경우 이사장이 각급학교에 교원의 파견를 요\n    청할 수 있도록 함(안 제24조)\n\n15. 공사로 하여금 다음 각호의 업무를 행하도록 함. 라디오 및 텔레비전 교육방송 실시 방송시설의 설치 운영 \n    및 관리 프로그램 제작 및 공급사업 교육관련행사 등의 주관 및 국제교류 교육방송에 관한 조사 연구전속\n    단체의 관리 운영 등\n\n16. 공사의 경비는 방송발전기금의 일부로 하되 필요에 따라 이사회의 의결과 방송위원회의 승인을 통해 기타 \n    재원을 운용할 수 있도록 함. 다만, 방송발전기금 중 교육방송 지원금의 규모는 방송위원회에서 정하도록 \n    함(안 제28조)\n\n17. 이 법 시행 당시 한국교육개발원 부설 교육방송이 소유하는 시설과 재산에 관한 권리 의무를 공사가 승계\n    하도록 함(안 부칙 제2조)"
    },
    " 소관위 심사정보": {
        "소관위원회": [
            "교육위원회"
        ],
        "회부일": [
            "1997-11-14"
        ],
        "상정일": [
            ""
        ],
        "처리일": [
            ""
        ],
        "처리결과": [
            ""
        ],
        "문서": [
            ""
        ]
    },
    "관련위 심사정보": {
        "관련위원회": [
            "재정경제위원회"
        ],
        "회부일": [
            "1997-11-14"
        ],
        "상정일": [
            ""
        ],
        "의견서제시일": [
            ""
        ],
        "문서": [
            ""
        ]
    },
    "본회의 심의정보": {
        "상정일": [
            ""
        ],
        "의결일": [
            "1999-07-03"
        ],
        "회의명": [
            ""
        ],
        "회의결과": [
            "철회"
        ],
        "회의록": [
            ""
        ]
    }
}