{
    "의안접수정보": {
        "의안번호": [
            "2011172"
        ],
        "제안일자": [
            "2017-12-29"
        ],
        "제안자": [
            "이만희의원등11인"
        ],
        "문서": [
            "의안원문"
        ],
        "제안회기": [
            "제20대(2016~2020)제355회"
        ],
        "제안이유 및 주요내용": "제안이유 및 주요내용\n\n  현행법에서는 사회적책임경영 중소기업지원센터가 법률에 따른 지정기준에 미달하게 되는 경우에는 지정을 취소할 수 있도록 규정하고, 구체적인 지정취소의 기준ㆍ절차 등에 대해서는 대통령령으로 정하도록 하고 있음.\n  그런데 동법 시행령에서는 법률에서 정하고 있는 취소사유 외에 거짓이나 그 밖의 부당한 방법으로 지정을 받은 경우와 정당한 사유 없이 사업계획서에 따른 업무를 3개월 이상 수행하지 아니한 경우도 지정취소 사유로 추가하고 있어 법률의 위임범위를 일탈한 것이라는 지적이 있음.\n  이에 지정취소는 침익적인 행정처분에 해당하므로 법률에서 지정취소 사유를 구체적으로 규정하고 위반행위의 태양과 성격을 고려하여 강행적 취소와 재량적 취소로 구분하여 위임하려는 것임(안 제62조의9제4항)."
    },
    " 소관위 심사정보": {
        "소관위원회": [
            "산업통상자원중소벤처기업위원회"
        ],
        "회부일": [
            "2018-01-02"
        ],
        "상정일": [
            "2018-02-12"
        ],
        "처리일": [
            "2018-11-29"
        ],
        "처리결과": [
            "대안반영폐기"
        ],
        "문서": [
            "검토보고서심사보고서"
        ]
    },
    "소관위 회의정보": {
        "회의명": [
            "제356회국회(임시회)제1차전체회의",
            "제364회국회(정기회)제4차중소벤처기업소위"
        ],
        "회의일": [
            "2018-02-12",
            "2018-11-27"
        ],
        "회의결과": [
            "상정/제안설명/검토보고/대체토론/소위회부",
            "상정/의결(대안반영폐기)"
        ],
        "회의록": [
            "",
            ""
        ]
    },
    "본회의 심의정보": {
        "상정일": [
            ""
        ],
        "의결일": [
            "2018-12-07"
        ],
        "회의명": [
            ""
        ],
        "회의결과": [
            "대안반영폐기"
        ],
        "회의록": [
            ""
        ]
    }
}