{
    "의안접수정보": {
        "의안번호": [
            "2013230"
        ],
        "제안일자": [
            "2018-04-24"
        ],
        "제안자": [
            "김병관의원등11인"
        ],
        "문서": [
            "의안원문비용추계서"
        ],
        "제안회기": [
            "제20대(2016~2020)제359회"
        ],
        "제안이유 및 주요내용": "제안이유 및 주요내용\n\n  불특정 다수의 사람이 이용하는 공중화장실에서 여성을 대상으로 한 성범죄, 폭력 등 강력범죄 사건이 계속 발생하고 있으나 화장실은 폐쇄적이고 사적인 공간이므로 다른 사람에게 손쉽게 도움을 요청하기 어려운 문제가 있음.\n  이러한 문제를 해결하기 위해 일부 지방자치단체에서는 강력범죄 사건 발생을 방지하고 여성이 안전하게 이용할 수 있도록 하기 위해 조례를 제정하여 화장실 내부에 비상벨을 설치하고 있음.\n  그러나 대부분의 지방자치단체는 예산이 부족하여 비상벨 설치를 하지 못하고 있으며, 설치를 한 경우에도 관리비용 부족으로 제대로 관리되지 못하고 있는 것으로 보임.\n  이에 공중화장실에 비상벨을 의무적으로 설치하도록 하고, 국가 및 지방자치단체는 그 설치 및 관리비용을 보조할 수 있도록 규정함으로써 공중화장실을 안심하고 이용할 수 있게 하려는 것임(안 제7조제4항 및 제12조제2항 신설 등)."
    },
    " 소관위 심사정보": {
        "소관위원회": [
            "행정안전위원회"
        ],
        "회부일": [
            "2018-04-25"
        ],
        "상정일": [
            "2018-08-21"
        ],
        "처리일": [
            ""
        ],
        "처리결과": [
            ""
        ],
        "문서": [
            "검토보고서"
        ]
    },
    "소관위 회의정보": {
        "회의명": [
            "제363회국회(임시회)제1차전체회의"
        ],
        "회의일": [
            "2018-08-21"
        ],
        "회의결과": [
            "상정/제안설명/검토보고/대체토론/소위회부"
        ],
        "회의록": [
            ""
        ]
    },
    "본회의 심의정보": {
        "상정일": [
            ""
        ],
        "의결일": [
            "2020-05-29"
        ],
        "회의명": [
            ""
        ],
        "회의결과": [
            "임기만료폐기"
        ],
        "회의록": [
            ""
        ]
    }
}