{
    "의안접수정보": {
        "의안번호": [
            "171452"
        ],
        "제안일자": [
            "2005-03-02"
        ],
        "제안자": [
            "이규택의원등10인"
        ],
        "문서": [
            "의안원문"
        ],
        "제안회기": [
            "제17대(2004~2008)제252회"
        ],
        "제안이유 및 주요내용": "■ 제안이유\n\n  최근 대학수학능력시험에서 휴대전화기를 이용한 부정행위로 인하여 그 수단과 방법이 사회적으로 문제가 되고 있는 바, 이를 방지하기 위한 방안의 일환으로 휴대전화기의 전파를 차단할 수 있는 법적근거를 새로이 마련하려는 것임.\n\n\n\n■ 주요내용\n\n  교육인적자원부장관은 대학수학능력시험을 시행함에 있어 휴대전화를 이용한 부정행위를 방지하기 위하여 정보통신부장관에게 전파방해 등을 요청할 수 있도록 함(안 제34조제5항 신설)."
    },
    " 소관위 심사정보": {
        "소관위원회": [
            "교육위원회"
        ],
        "회부일": [
            "2005-03-04"
        ],
        "상정일": [
            "2005-04-19"
        ],
        "처리일": [
            ""
        ],
        "처리결과": [
            ""
        ],
        "문서": [
            "검토보고서"
        ]
    },
    "관련위 심사정보": {
        "관련위원회": [
            "과학기술정보통신위원회"
        ],
        "회부일": [
            "2005-03-04"
        ],
        "상정일": [
            "2006-04-17"
        ],
        "의견서제시일": [
            "2006-06-27"
        ],
        "문서": [
            "의견서"
        ]
    },
    "본회의 심의정보": {
        "상정일": [
            ""
        ],
        "의결일": [
            "2008-05-29"
        ],
        "회의명": [
            ""
        ],
        "회의결과": [
            "임기만료폐기"
        ],
        "회의록": [
            ""
        ]
    }
}