{
    "의안접수정보": {
        "의안번호": [
            "174270"
        ],
        "제안일자": [
            "2006-04-18"
        ],
        "제안자": [
            "이은영의원등10인"
        ],
        "문서": [
            "의안원문"
        ],
        "제안회기": [
            "제17대(2004~2008)제259회"
        ],
        "제안이유 및 주요내용": "■ 제안이유\n종이문서인 어음은 그 물리적 본질로 인해 분할이 불가능하므로, 어음의 수취인이 그 어음을 다시 지급수단으로 활용하고자 하는 단계에서는 어음의 액면금액과 지급할 금액이 불일치하여 활용이 불가능하거나 정산을 위해 별도로 현금을 준비해야하는 등 불편이 매우 큼. 따라서 어음소지인이 용도에 따라 어음금을 분할하여 사용할 수 있다면 상거래의 합리화 및 상인의 편의를 도모할 수 있음. 전자어음은 종이어음과 같이 기능적 장애가 없으므로, 전자적인 방법으로 어음을 발행·유통하는 경우 어음을 분할할 수 있도록 법적 장치를 보완해야 함. 전자어음분할제도의 도입은 기업으로 하여금 필요한 자금만 일부 할인할 수 있어 이자비용을 절감할 수 있는 등 기업의 경쟁력 향상에 도움이 되며, 특히 대기업의 하청기업, 중소기업, 영세상인 등에게 혁신적인 경제적 편익을 제공하게 될 것임. \n\n\n\n\n■ 주요내용\n\n  전자어음을 분할하여 그 일부에 관해 각각 배서할 수 있도록 함(안 제7조의2)."
    },
    " 소관위 심사정보": {
        "소관위원회": [
            "법제사법위원회"
        ],
        "회부일": [
            "2006-04-19"
        ],
        "상정일": [
            "2007-11-21"
        ],
        "처리일": [
            "2007-11-21"
        ],
        "처리결과": [
            "폐기"
        ],
        "문서": [
            "검토보고서심사보고서"
        ]
    },
    "소관위 회의정보": {
        "회의명": [
            "제268회국회(임시회)제5차법안심사제1소위",
            "제268회국회(임시회)제8차법안심사제1소위",
            "제269회국회(정기회)제3차법안심사제1소위"
        ],
        "회의일": [
            "2007-06-22",
            "2007-08-08",
            "2007-11-20"
        ],
        "회의결과": [
            "상정",
            "상정",
            "상정/의결(본회의에부의하지아니하기로의결)"
        ],
        "회의록": [
            "",
            "",
            ""
        ]
    },
    "본회의 심의정보": {
        "상정일": [
            ""
        ],
        "의결일": [
            "2008-03-06"
        ],
        "회의명": [
            ""
        ],
        "회의결과": [
            "폐기"
        ],
        "회의록": [
            ""
        ]
    }
}