{
    "의안접수정보": {
        "의안번호": [
            "1905596"
        ],
        "제안일자": [
            "2013-06-24"
        ],
        "제안자": [
            "기획재정위원장"
        ],
        "문서": [
            "의안원문"
        ],
        "제안회기": [
            "제19대(2012~2016)제316회"
        ],
        "제안이유 및 주요내용": "■ 제안이유 \n 현재 조달에 관한 통계가 통합적으로 취합·관리되지 못하고 있어 공공기관에 의한 조달규모의 정확한 파악 및 효과적인 조달정책 수립에 한계가 있으므로 조달청이 조달사업에 관한 통계를 작성하고 필요한 자료를 각 기관에 요구할 수 있도록 하고, 자유무역협정 체결 확대 등으로 공공조달시장의 개방이 가속화 되고 있으나 우리 기업의 해외 조달시장 진출은 매우 미흡한 실정이므로 조달사업의 범위에 국제조달 협력 및 해외조달시장 진출 지원기능을 명시하도록 함.\n\n■ 주요내용 \n가. 조달청이 조달사업에 관한 통계를 작성하고 필요한 자료를 각 기관에 요구할 수 있도록 함(안 제3조의5 신설).\n나. 조달사업의 범위에 국제조달 협력 및 해외조달시장 진출 지원 기능을 명시하고, 국내 기업의 해외 조달시장 진출을 지원하기 위해 필요한 조치를 할 수 있도록 함(안 제3조의6 신설)."
    },
    " 소관위 심사정보": {
        "소관위원회": [
            "기획재정위원회"
        ],
        "회부일": [
            ""
        ],
        "상정일": [
            ""
        ],
        "처리일": [
            ""
        ],
        "처리결과": [
            "대안가결"
        ],
        "문서": [
            "위원회제출안"
        ]
    },
    "법사위 체계자구심사정보": {
        "공포일자": [
            "2013-07-16"
        ],
        "공포번호": [
            "11888"
        ],
        "공포법률": [
            "조달사업에관한법률"
        ]
    },
    "법사위 회의정보": {
        "회의명": [
            "제316회국회(임시회)제3차전체회의"
        ],
        "회의일": [
            "2013-06-20"
        ],
        "회의결과": [
            "상정/제안설명/검토보고/대체토론/의결(수정가결)"
        ],
        "회의록": [
            ""
        ]
    },
    "본회의 심의정보": {
        "상정일": [
            "2013-06-25"
        ],
        "의결일": [
            "2013-06-25"
        ],
        "회의명": [
            "제316회제8차"
        ],
        "회의결과": [
            "원안가결"
        ],
        "회의록": [
            ""
        ]
    },
    "정부이송정보": {
        "정부이송일": [
            "2013-07-05"
        ]
    }
}