{
    "의안접수정보": {
        "의안번호": [
            "1800987"
        ],
        "제안일자": [
            "2008-09-23"
        ],
        "제안자": [
            "양정례의원등13인"
        ],
        "문서": [
            "의안원문"
        ],
        "제안회기": [
            "제18대(2008~2012)제278회"
        ],
        "제안이유 및 주요내용": "제안이유\n  아파트 등 공동주택의 외벽도색, 승강기 교체 및 로프 교체, 옥상방수 공사 등과 같이 일시적이고 소액 규모의 수선유지비로 사용하기 어려운 장기간에 걸친 대규모의 수선공사에 사용하기 위하여 적립해 놓는 돈을 장기수선충당금이라 한다.  이 장기수선충당금은 공동주택 관리비에 포함되어 부과되고 주택법 제51조 제1항에 의하여 당해 공동주택의 소유자가 납부해야 할 의무가 있음.  또한 동법 제101조 제2항에 의하면 장기수선충당금을 적립하지 아니한 자는 5백만원 이하의 과태료에 처하게 되어 있음. \n  그런데 실생활에서는 전ㆍ월세 세입자가 소유자에게 납부의무가 있다는 사실을 모르고 장기수선충당금을 납부하는 경우가 많아서, 전ㆍ월세 계약해지 또는 만료 시에 세입자가 뒤늦게 알고서 기납부한 장기수선충당금의 반환을 요구하는 경우가 더러 있을 뿐, 대부분의 경우에는 세입자가 그 사실을 모르고 지나치는 것이 현실임.\n  따라서 공동주택의 소유자와 부동산 중개업자가 전ㆍ월세 계약 시에 세입자에게 장기수선충당금의 납부의무가 소유자에게 있다는 사실을 고지해 줌으로써, 세입자의 피해 예방은 물론 실생활에서 일어나는 분쟁을 미연에 방지할 필요가 있음.\n\n\n주요내용\n  가. 공동주택의 전ㆍ월세 계약체결 시 당해 주택의 소유자와 당해 주택을 중개한 부동산 중개업자는 세입자에게 장기수선충당금 납부의무가 소유자에게 있음을 고지하도록 함(안 제51조제4항 신설).\n  나. 이 고지의무를 이행하지 아니한 자는 5백만원 이하의 과태료에 처하도록 함(안 제101조제2항제16호)."
    },
    " 소관위 심사정보": {
        "소관위원회": [
            "국토해양위원회"
        ],
        "회부일": [
            "2008-09-25"
        ],
        "상정일": [
            "2008-12-03"
        ],
        "처리일": [
            "2011-11-17"
        ],
        "처리결과": [
            "폐기"
        ],
        "문서": [
            "검토보고서심사보고서"
        ]
    },
    "소관위 회의정보": {
        "회의명": [
            "제278회국회(정기회)제12차전체회의",
            "제279회국회(임시회)제3차법안심사소위",
            "제303회국회(정기회)제4차법안심사소위"
        ],
        "회의일": [
            "2008-12-03",
            "2008-12-12",
            "2011-11-15"
        ],
        "회의결과": [
            "상정/제안설명/검토보고/대체토론/소위회부",
            "상정/축조심사",
            "축조심사/의결(본회의에부의하지아니하기로의결)"
        ],
        "회의록": [
            "",
            "",
            ""
        ]
    },
    "본회의 심의정보": {
        "상정일": [
            ""
        ],
        "의결일": [
            "2011-12-29"
        ],
        "회의명": [
            ""
        ],
        "회의결과": [
            "폐기"
        ],
        "회의록": [
            ""
        ]
    }
}