{
    "의안접수정보": {
        "의안번호": [
            "1800568"
        ],
        "제안일자": [
            "2008-08-07"
        ],
        "제안자": [
            "강길부의원등12인"
        ],
        "문서": [
            "의안원문"
        ],
        "제안회기": [
            "제18대(2008~2012)제277회"
        ],
        "제안이유 및 주요내용": "제안이유 \n  산업단지 입주기업의 물류비 절감, 물류기업의 경쟁력 강화 등을 위해 물류기업이 산업단지 내 산업시설용지에 입주하여 당해 용지를 조성원가로 공급받을 수 있도록 하고, 대규모 일반산업단지에 대한 국토해양부장관의 승인제도를 폐지하여 지방자치단체의 자율권을 강화하며, 산업단지지정권자와 기업이 입주협약서를 체결하는 등 기업수요가 확인된 경우에는 미분양비율 등에 의한 산업단지지정제한을 받지 않도록 하여 산업단지가 보다 탄력적으로 공급될 수 있도록 하고, 개별공장의 효율적인 정비를 위해 준산업단지의 지정권자를 확대하고 기반시설 지원규정을 신설하고자 함.\n\n주요내용\n  가. 산업단지 및 산업단지개발사업에 물류시설을 추가함(안 제2조제4호의2 신설 및 제2조제5호·제6호).\n  나. 대통령령이 정하는 면적 이상의 일반산업단지를 지정하는 경우에는 국토해양부장관의 승인을 얻도록 하는 규정을 삭제하여 국토해양부장관의 승인제도를 폐지함(제7조제3항 및 제4항 삭제).\n  다. 산업단지 지정권자와 기업이 입주협약서를 체결하는 등 객관적으로 기업의 입주수요가 확인된 경우에는 미분양비율 등에 의한 산업단지지정제한을 받지 않도록 함(안 제8조의2).\n  라. 준산업단지 지정권자에 특별시장·광역시장을 추가하고, 도로 등 기반시설 지원이 원활히 이루어질 수 있도록 지원제도를 신설함(안 제8조의3제1항 및 제5항)."
    },
    " 소관위 심사정보": {
        "소관위원회": [
            "국토해양위원회"
        ],
        "회부일": [
            "2008-08-29"
        ],
        "상정일": [
            "2008-11-20"
        ],
        "처리일": [
            "2008-11-27"
        ],
        "처리결과": [
            "대안반영폐기"
        ],
        "문서": [
            "검토보고서심사보고서"
        ]
    },
    "소관위 회의정보": {
        "회의명": [
            "제278회국회(정기회)제10차전체회의",
            "제278회국회(정기회)제2차법안심사소위"
        ],
        "회의일": [
            "2008-11-20",
            "2008-11-26"
        ],
        "회의결과": [
            "상정/제안설명/검토보고/대체토론/소위회부",
            "상정/의결(대안반영폐기)"
        ],
        "회의록": [
            "",
            ""
        ]
    },
    "본회의 심의정보": {
        "상정일": [
            ""
        ],
        "의결일": [
            "2008-12-05"
        ],
        "회의명": [
            ""
        ],
        "회의결과": [
            "대안반영폐기"
        ],
        "회의록": [
            ""
        ]
    }
}