{
    "의안접수정보": {
        "의안번호": [
            "1812914"
        ],
        "제안일자": [
            "2011-08-18"
        ],
        "제안자": [
            "박은수의원등11인"
        ],
        "문서": [
            "의안원문"
        ],
        "제안회기": [
            "제18대(2008~2012)제302회"
        ],
        "제안이유 및 주요내용": "제안이유 및 주요내용\n\n  형사절차상 피고인의 방어권 보장을 위하여 각종 서류나 증거물 등에 대한 열람？등사권이 인정되고 있으나, 이로 인하여 오히려 범죄신고자 등의 인적사항이 노출되고 보복범죄로 이어지는 등 부작용이 있을 수 있음.\n  현행법은 이러한 문제를 해결하기 위하여 조서 등 서류를 작성함에 있어 특정범죄 신고자 등의 인적사항을 기재하지 아니할 수 있도록 하고 있으나, 사후적인 삭제에 대한 근거가 불분명한 점 등 제도상의 일부 미비점이 있어, 이미 기재된 인적 사항의 사후적인 삭제가 가능하도록 그 근거를 명시하고, 인적 사항을 기재하지 아니하거나 삭제하도록 신청할 수 있음을 특정범죄 신고자 등에게 고지하도록 하는 등 제도를 보완하려는 것임(안 제7조제1항？제5항？제7항？제8항 및 안 제11조제2항？제5항？제8항 등)."
    },
    " 소관위 심사정보": {
        "소관위원회": [
            "법제사법위원회"
        ],
        "회부일": [
            "2011-08-19"
        ],
        "상정일": [
            "2011-11-09"
        ],
        "처리일": [
            ""
        ],
        "처리결과": [
            ""
        ],
        "문서": [
            "검토보고서"
        ]
    },
    "소관위 회의정보": {
        "회의명": [
            "제303회국회(정기회)제11차전체회의"
        ],
        "회의일": [
            "2011-11-09"
        ],
        "회의결과": [
            "상정/제안설명/검토보고/대체토론/소위회부"
        ],
        "회의록": [
            ""
        ]
    },
    "본회의 심의정보": {
        "상정일": [
            ""
        ],
        "의결일": [
            "2012-05-29"
        ],
        "회의명": [
            ""
        ],
        "회의결과": [
            "임기만료폐기"
        ],
        "회의록": [
            ""
        ]
    }
}